pymcuprog/__init__.py
pymcuprog/avr32target.py
pymcuprog/avr8target.py
pymcuprog/avrdebugger.py
pymcuprog/backend.py
pymcuprog/hexfileutils.py
pymcuprog/logging.yaml
pymcuprog/nvm.py
pymcuprog/nvmavr32.py
pymcuprog/nvmdebugwire.py
pymcuprog/nvmmegaavrjtag.py
pymcuprog/nvmmzeroplus.py
pymcuprog/nvmpic.py
pymcuprog/nvmserialupdi.py
pymcuprog/nvmspi.py
pymcuprog/nvmtpi.py
pymcuprog/nvmupdi.py
pymcuprog/nvmxmega.py
pymcuprog/programmer.py
pymcuprog/pymcuprog.py
pymcuprog/pymcuprog_errors.py
pymcuprog/pymcuprog_main.py
pymcuprog/samtarget.py
pymcuprog/toolconnection.py
pymcuprog/utils.py
pymcuprog/deviceinfo/__init__.py
pymcuprog/deviceinfo/configgenerator.py
pymcuprog/deviceinfo/deviceinfo.py
pymcuprog/deviceinfo/deviceinfokeys.py
pymcuprog/deviceinfo/eraseflags.py
pymcuprog/deviceinfo/generate_device_info.py
pymcuprog/deviceinfo/generateconfig.py
pymcuprog/deviceinfo/harvest.py
pymcuprog/deviceinfo/memorynames.py
pymcuprog/deviceinfo/devices/__init__.py
pymcuprog/deviceinfo/devices/atmega1608.py
pymcuprog/deviceinfo/devices/atmega1609.py
pymcuprog/deviceinfo/devices/atmega3208.py
pymcuprog/deviceinfo/devices/atmega3209.py
pymcuprog/deviceinfo/devices/atmega324pb.py
pymcuprog/deviceinfo/devices/atmega328p.py
pymcuprog/deviceinfo/devices/atmega4808.py
pymcuprog/deviceinfo/devices/atmega4809.py
pymcuprog/deviceinfo/devices/atmega808.py
pymcuprog/deviceinfo/devices/atmega809.py
pymcuprog/deviceinfo/devices/atsamd21e18a.py
pymcuprog/deviceinfo/devices/atsamd21g18a.py
pymcuprog/deviceinfo/devices/atsamd21j18a.py
pymcuprog/deviceinfo/devices/attiny104.py
pymcuprog/deviceinfo/devices/attiny1604.py
pymcuprog/deviceinfo/devices/attiny1606.py
pymcuprog/deviceinfo/devices/attiny1607.py
pymcuprog/deviceinfo/devices/attiny1614.py
pymcuprog/deviceinfo/devices/attiny1616.py
pymcuprog/deviceinfo/devices/attiny1617.py
pymcuprog/deviceinfo/devices/attiny1624.py
pymcuprog/deviceinfo/devices/attiny1626.py
pymcuprog/deviceinfo/devices/attiny1627.py
pymcuprog/deviceinfo/devices/attiny202.py
pymcuprog-3.19.4.61.dist-info/licenses/LICENSE.txt
pymcuprog-3.19.4.61.dist-info/METADATA
pymcuprog-3.19.4.61.dist-info/WHEEL
pymcuprog-3.19.4.61.dist-info/entry_points.txt
pymcuprog-3.19.4.61.dist-info/top_level.txt
pymcuprog-3.19.4.61.dist-info/RECORD
