Metadata-Version: 2.4
Name: pymcuprog
Version: 3.19.4.61
Summary: Tools for programming of MCUs using Microchip CMSIS-DAP based debuggers
Author: Microchip Technology
Author-email: support@microchip.com
License: MIT
Keywords: Microchip,nEDBG,Curiosity Nano,PKOB nano,debugger
Classifier: Development Status :: 5 - Production/Stable
Classifier: Intended Audience :: Developers
Classifier: Topic :: Software Development :: Embedded Systems
Classifier: Programming Language :: Python :: 3
Classifier: Programming Language :: Python :: 3.9
Classifier: Programming Language :: Python :: 3.10
Classifier: Programming Language :: Python :: 3.11
Classifier: Programming Language :: Python :: 3.12
Classifier: Programming Language :: Python :: 3.13
Classifier: Operating System :: Microsoft :: Windows
Classifier: Operating System :: POSIX :: Linux
Classifier: Operating System :: MacOS
Classifier: License :: OSI Approved :: MIT License
Requires-Python: >=2.7
License-File: LICENSE.txt
Requires-Dist: pyserial
Requires-Dist: IntelHex
Requires-Dist: PyYAML
Requires-Dist: appdirs
Requires-Dist: pathlib2; python_version < "3"
Requires-Dist: pyedbglib~=2.24
Provides-Extra: dev
Requires-Dist: pylint>=2.15; extra == "dev"
Provides-Extra: test
Requires-Dist: mock; extra == "test"
Requires-Dist: parameterized; extra == "test"
Requires-Dist: pytest; extra == "test"
Provides-Extra: doc
Requires-Dist: mock; extra == "doc"
Requires-Dist: sphinx; extra == "doc"
Dynamic: license-file
